{
  "metadata": {
    "version": "1.0",
    "last_updated": "2025-01-13T00:13:37-05:00"
  },
  "name": "Mossthorn",
  "stars": "2",
  "ranks": {
    "1": {
      "effects": [
        {
          "type": "proc_effect",
          "description": "Taking damage activates Mossthorn for 6 seconds. While active, each attack you receive triggers a retaliatory piercing thorn (no more than once every 0.5 seconds), dealing 17% base damage + 201 to enemies",
          "conditions": [
            "on_damage_taken",
            "cooldown_restriction"
          ],
          "value": 17.0,
          "duration": 6.0,
          "cooldown": 0.5
        }
      ]
    },
    "2": {
      "effects": [
        {
          "type": "damage_effect",
          "description": "Retaliatory thorn damage increased to 22% base damage + 201",
          "conditions": [],
          "value": 22.0
        }
      ]
    },
    "3": {
      "effects": [
        {
          "type": "damage_effect",
          "description": "While Mossthorn is active, damage you take is reduced by 2%",
          "conditions": [],
          "value": 2.0
        }
      ]
    },
    "4": {
      "effects": [
        {
          "type": "damage_effect",
          "description": "Retaliatory thorn damage increased to 28% base damage + 201",
          "conditions": [],
          "value": 28.0
        }
      ]
    },
    "5": {
      "effects": [
        {
          "type": "damage_effect",
          "description": "While Mossthorn is active, damage you take is reduced by 4%",
          "conditions": [],
          "value": 4.0
        }
      ]
    },
    "6": {
      "effects": [
        {
          "type": "utility_effect",
          "description": "TODO: Rank information needed",
          "conditions": []
        }
      ]
    },
    "7": {
      "effects": [
        {
          "type": "utility_effect",
          "description": "TODO: Rank information needed",
          "conditions": []
        }
      ]
    },
    "8": {
      "effects": [
        {
          "type": "utility_effect",
          "description": "TODO: Rank information needed",
          "conditions": []
        }
      ]
    },
    "9": {
      "effects": [
        {
          "type": "utility_effect",
          "description": "TODO: Rank information needed",
          "conditions": []
        }
      ]
    },
    "10": {
      "effects": [
        {
          "type": "proc_effect",
          "description": "Taking damage activates Mossthorn for 6 seconds. While active, each attack you receive triggers a retaliatory piercing thorn (no more than once every 0.5 seconds), dealing 50% base damage + 201 to enemies. While Mossthorn is active, damage you take is reduced by 8%",
          "conditions": [
            "on_damage_taken",
            "cooldown_restriction"
          ],
          "value": 50.0,
          "duration": 6.0,
          "cooldown": 0.5
        }
      ]
    }
  },
  "max_rank": 10,
  "magic_find": "5",
  "max_effect": "Taking damage activates Mossthorn for 6 seconds. While active, each attack you receive triggers a retaliatory piercing thorn (no more than once every 0.5 seconds), dealing 50% base damage + 201 to enemies. Cannot activate more often than once every 20 seconds. While Mossthorn is active, damage you take is reduced by 8%",
  "description": "Taking damage activates Mossthorn for Ts. While active, each attack you receive triggers a retaliatory piercing thorn (no more than once every Ts), dealing X% base damage + 201 to enemies. While Mossthorn is active, damage you take is reduced by X%"
}